<?xml version="1.0" encoding="utf-8"?>
<class id="a5c5dd7a-6cb5-4d03-931e-105ba92119a0" type="Folder" typeId="3407a825-1331-4f3f-89a4-901903ed97ce">
  <name>Models</name>
  <display>Models</display>
  <isAbstract>false</isAbstract>
  <genericTypes />
  <isMapped>false</isMapped>
  <parentFolderId>a5308ad9-6b01-4890-8f42-a33891fae42c</parentFolderId>
  <stereotypes />
  <metadata />
  <childElements>
    <childElement id="f01cbfd7-4d84-4c76-a928-69395f1c46ca" type="Template Output" typeId="d421c322-7a51-4094-89fa-e5d8a0a97b27">
      <name>Intent.Application.Identity.ResultModel</name>
      <display>Intent.Application.Identity.ResultModel</display>
      <externalReference>Intent.Application.Identity</externalReference>
      <isAbstract>false</isAbstract>
      <genericTypes />
      <isMapped>false</isMapped>
      <parentFolderId>a5c5dd7a-6cb5-4d03-931e-105ba92119a0</parentFolderId>
      <stereotypes />
      <metadata>
        <entry key="status" value="assigned" />
      </metadata>
      <childElements />
    </childElement>
    <childElement id="305f4a75-7ed8-449a-a322-0f26a04297be" type="Template Output" typeId="d421c322-7a51-4094-89fa-e5d8a0a97b27">
      <name>Intent.MediatR.DomainEvents.DomainEventNotification</name>
      <display>Intent.MediatR.DomainEvents.DomainEventNotification</display>
      <externalReference>Intent.MediatR.DomainEvents</externalReference>
      <isAbstract>false</isAbstract>
      <genericTypes />
      <isMapped>false</isMapped>
      <parentFolderId>a5c5dd7a-6cb5-4d03-931e-105ba92119a0</parentFolderId>
      <stereotypes />
      <metadata>
        <entry key="status" value="assigned" />
      </metadata>
      <childElements />
    </childElement>
  </childElements>
</class>